osx_photo_archiver/__init__.py
osx_photo_archiver/cli.py
osx_photo_archiver/core.py
osx_photo_archiver-0.1.2.dist-info/LICENSE
osx_photo_archiver-0.1.2.dist-info/METADATA
osx_photo_archiver-0.1.2.dist-info/WHEEL
osx_photo_archiver-0.1.2.dist-info/entry_points.txt
osx_photo_archiver-0.1.2.dist-info/top_level.txt
osx_photo_archiver-0.1.2.dist-info/RECORD
