Metadata-Version: 2.2
Name: osx-photo-archiver
Version: 0.1.2
Summary: macOSのPhotosアプリから写真・動画を年/月ディレクトリ構造でエクスポートするツール
Author-email: 村田 篤郎 <murata.atsuo.95@gmail.com>
License: MIT
Project-URL: Homepage, https://github.com/amurata/osx-photo-archiver
Keywords: photos,macos,organization,export
Classifier: Development Status :: 3 - Alpha
Classifier: Intended Audience :: End Users/Desktop
Classifier: License :: OSI Approved :: MIT License
Classifier: Operating System :: MacOS :: MacOS X
Classifier: Programming Language :: Python :: 3
Classifier: Programming Language :: Python :: 3.8
Classifier: Programming Language :: Python :: 3.9
Classifier: Programming Language :: Python :: 3.10
Classifier: Topic :: Multimedia :: Graphics
Classifier: Topic :: Utilities
Requires-Python: >=3.8
License-File: LICENSE
Requires-Dist: osxphotos>=0.28.5
Requires-Dist: python-dateutil>=2.8.2
Requires-Dist: click>=8.0.0
Provides-Extra: dev
Requires-Dist: pytest>=7.0.0; extra == "dev"
Requires-Dist: black>=22.0.0; extra == "dev"
Requires-Dist: flake8>=4.0.0; extra == "dev"
Requires-Dist: mypy>=0.900; extra == "dev"
